dagster_dlt/__init__.py
dagster_dlt/asset_decorator.py
dagster_dlt/constants.py
dagster_dlt/dlt_event_iterator.py
dagster_dlt/py.typed
dagster_dlt/resource.py
dagster_dlt/translator.py
dagster_dlt/version.py
dagster_dlt/components/__init__.py
dagster_dlt/components/dlt_load_collection/__init__.py
dagster_dlt/components/dlt_load_collection/component.py
dagster_dlt/components/dlt_load_collection/scaffolder.py
dagster_dlt-0.28.13.dist-info/licenses/LICENSE
dagster_dlt-0.28.13.dist-info/METADATA
dagster_dlt-0.28.13.dist-info/WHEEL
dagster_dlt-0.28.13.dist-info/entry_points.txt
dagster_dlt-0.28.13.dist-info/top_level.txt
dagster_dlt-0.28.13.dist-info/RECORD
